<annotation>
	<folder>for_labeling</folder>
	<filename>g_banana_00164.jpg</filename>
	<path>/Users/cristy/Desktop/ObjectDetector/Tensorflow/workspace/images/for_labeling/g_banana_00164.jpg</path>
	<source>
		<database>Unknown</database>
	</source>
	<size>
		<width>2016</width>
		<height>1134</height>
		<depth>3</depth>
	</size>
	<segmented>0</segmented>
	<object>
		<name>Banana</name>
		<pose>Unspecified</pose>
		<truncated>0</truncated>
		<difficult>0</difficult>
		<bndbox>
			<xmin>211</xmin>
			<ymin>102</ymin>
			<xmax>854</xmax>
			<ymax>1023</ymax>
		</bndbox>
	</object>
	<object>
		<name>Banana</name>
		<pose>Unspecified</pose>
		<truncated>0</truncated>
		<difficult>0</difficult>
		<bndbox>
			<xmin>954</xmin>
			<ymin>115</ymin>
			<xmax>1413</xmax>
			<ymax>847</ymax>
		</bndbox>
	</object>
</annotation>
