<annotation>
	<folder>for_labeling</folder>
	<filename>g_banana_00149.jpg</filename>
	<path>/Users/cristy/Desktop/ObjectDetector/Tensorflow/workspace/images/for_labeling/g_banana_00149.jpg</path>
	<source>
		<database>Unknown</database>
	</source>
	<size>
		<width>474</width>
		<height>355</height>
		<depth>3</depth>
	</size>
	<segmented>0</segmented>
	<object>
		<name>Banana</name>
		<pose>Unspecified</pose>
		<truncated>0</truncated>
		<difficult>0</difficult>
		<bndbox>
			<xmin>17</xmin>
			<ymin>23</ymin>
			<xmax>450</xmax>
			<ymax>298</ymax>
		</bndbox>
	</object>
</annotation>
